send2trash/IFileOperationProgressSink.py
send2trash/__init__.py
send2trash/__main__.py
send2trash/compat.py
send2trash/exceptions.py
send2trash/plat_gio.py
send2trash/plat_osx.py
send2trash/plat_osx_ctypes.py
send2trash/plat_osx_pyobjc.py
send2trash/plat_other.py
send2trash/plat_win.py
send2trash/plat_win_legacy.py
send2trash/plat_win_modern.py
Send2Trash-1.7.1.dist-info/LICENSE
Send2Trash-1.7.1.dist-info/METADATA
Send2Trash-1.7.1.dist-info/WHEEL
Send2Trash-1.7.1.dist-info/entry_points.txt
Send2Trash-1.7.1.dist-info/top_level.txt
Send2Trash-1.7.1.dist-info/RECORD
