Metadata-Version: 2.1
Name: Send2Trash
Version: 1.7.1
Summary: Send file to trash natively under Mac OS X, Windows and Linux.
Home-page: https://github.com/arsenetar/send2trash
Author: Andrew Senetar
Author-email: arsenetar@voltaicideas.net
License: BSD License
Project-URL: Bug Reports, https://github.com/arsenetar/send2trash/issues
Platform: UNKNOWN
Classifier: Development Status :: 5 - Production/Stable
Classifier: Intended Audience :: Developers
Classifier: License :: OSI Approved :: BSD License
Classifier: Operating System :: MacOS :: MacOS X
Classifier: Operating System :: Microsoft :: Windows
Classifier: Operating System :: POSIX
Classifier: Programming Language :: Python :: 2.7
Classifier: Programming Language :: Python :: 3
Classifier: Programming Language :: Python :: 3.4
Classifier: Programming Language :: Python :: 3.5
Classifier: Programming Language :: Python :: 3.6
Classifier: Programming Language :: Python :: 3.7
Classifier: Programming Language :: Python :: 3.8
Classifier: Programming Language :: Python :: 3.9
Classifier: Programming Language :: Python :: 3.10
Classifier: Topic :: Desktop Environment :: File Managers
Provides-Extra: win32
License-File: LICENSE
